ckzg.pypy310-pp73-aarch64-linux-gnu.so
ckzg-2.1.5.dist-info/METADATA
ckzg-2.1.5.dist-info/WHEEL
ckzg-2.1.5.dist-info/top_level.txt
ckzg-2.1.5.dist-info/RECORD
ckzg-2.1.5.dist-info/licenses/LICENSE
